luke_roberts_cloud_api/__init__.py
luke_roberts_cloud_api/const.py
luke_roberts_cloud_api/lamp.py
luke_roberts_cloud_api/luke_roberts_cloud.py
luke_roberts_cloud_api-0.0.17.dist-info/METADATA
luke_roberts_cloud_api-0.0.17.dist-info/WHEEL
luke_roberts_cloud_api-0.0.17.dist-info/licenses/LICENSE
luke_roberts_cloud_api-0.0.17.dist-info/RECORD
