Metadata-Version: 2.3
Name: luke_roberts_cloud_api
Version: 0.0.17
Summary: Exposes the API of the Luke Roberts cloud via utility classes. Luke Roberts is a Lighting Manufacturer.
Project-URL: Homepage, https://github.com/julian-lenz/Luke-Roberts-Cloud-API/tree/main
Project-URL: Issues, https://github.com/julian-lenz/Luke-Roberts-Cloud-API/issues
Author-email: Julian Lenzenweger <j.lenzenweger@gmail.com>
License-File: LICENSE
Classifier: License :: OSI Approved :: MIT License
Classifier: Operating System :: OS Independent
Classifier: Programming Language :: Python :: 3
Requires-Python: >=3.8
Requires-Dist: aiohttp
